speechaugs/__init__.py
speechaugs/speechaugs.py
speechaugs-0.0.11.dist-info/METADATA
speechaugs-0.0.11.dist-info/RECORD
speechaugs-0.0.11.dist-info/WHEEL
speechaugs-0.0.11.dist-info/top_level.txt
