Metadata-Version: 2.1
Name: speechaugs
Version: 0.0.11
Summary: Waveform augmentations
Home-page: https://github.com/waveletdeboshir/speechaugs/
Author: Darya Vozhdaeva
Author-email: daria-vozhdaeva@yandex.ru
License: UNKNOWN
Platform: UNKNOWN
Classifier: Programming Language :: Python :: 3.7
Classifier: License :: OSI Approved :: GNU General Public License v3 (GPLv3)
Requires-Dist: librosa (<=0.8.0,>=0.6.1)
Requires-Dist: colorednoise (>=1.1.1)
Requires-Dist: albumentations (>=0.1.12)
Requires-Dist: torchaudio (>=0.7.0)
